streamdeck_sdk_cli/__init__.py
streamdeck_sdk_cli/executable/__init__.py
streamdeck_sdk_cli/executable/executable.py
streamdeck_sdk_cli/executable/assets/DistributionTool
streamdeck_sdk_cli/executable/assets/DistributionTool.exe
streamdeck_sdk_cli/executable/assets/base_project/com.bestdeveloper.mytestplugin.sdPlugin/init.py
streamdeck_sdk_cli/executable/assets/base_project/com.bestdeveloper.mytestplugin.sdPlugin/manifest.json
streamdeck_sdk_cli/executable/assets/base_project/com.bestdeveloper.mytestplugin.sdPlugin/run.bat
streamdeck_sdk_cli/executable/assets/base_project/com.bestdeveloper.mytestplugin.sdPlugin/run.sh
streamdeck_sdk_cli/executable/assets/base_project/com.bestdeveloper.mytestplugin.sdPlugin/assets/category_icon.svg
streamdeck_sdk_cli/executable/assets/base_project/com.bestdeveloper.mytestplugin.sdPlugin/assets/plugin_icon.svg
streamdeck_sdk_cli/executable/assets/base_project/com.bestdeveloper.mytestplugin.sdPlugin/assets/myaction/action_icon.svg
streamdeck_sdk_cli/executable/assets/base_project/com.bestdeveloper.mytestplugin.sdPlugin/assets/myaction/key_icon.svg
streamdeck_sdk_cli/executable/assets/base_project/com.bestdeveloper.mytestplugin.sdPlugin/code/main.py
streamdeck_sdk_cli/executable/assets/base_project/com.bestdeveloper.mytestplugin.sdPlugin/code/requirements.txt
streamdeck_sdk_cli/executable/assets/base_project/com.bestdeveloper.mytestplugin.sdPlugin/code/settings.py
streamdeck_sdk_cli/executable/assets/base_project/com.bestdeveloper.mytestplugin.sdPlugin/property_inspector/myaction_pi.html
streamdeck_sdk_cli/executable/assets/base_project/com.bestdeveloper.mytestplugin.sdPlugin/property_inspector/myaction_pi.py
streamdeck_sdk_cli/executable/assets/base_project/com.bestdeveloper.mytestplugin.sdPlugin/property_inspector/pi_template.html
streamdeck_sdk_cli/executable/assets/base_project/com.bestdeveloper.mytestplugin.sdPlugin/property_inspector/streamdeck-javascript-sdk/assets/caret.svg
streamdeck_sdk_cli-0.0.2.dist-info/LICENSE
streamdeck_sdk_cli-0.0.2.dist-info/METADATA
streamdeck_sdk_cli-0.0.2.dist-info/WHEEL
streamdeck_sdk_cli-0.0.2.dist-info/entry_points.txt
streamdeck_sdk_cli-0.0.2.dist-info/top_level.txt
streamdeck_sdk_cli-0.0.2.dist-info/RECORD
