Metadata-Version: 2.1
Name: streamdeck_sdk_cli
Version: 0.0.2
Summary: Command Line Interface for streamdeck-python-sdk.
Author-email: Grigoriy Gusev <thegrigus@gmail.com>
Project-URL: Homepage, https://github.com/gri-gus/streamdeck-python-sdk-cli
Project-URL: Source, https://github.com/gri-gus/streamdeck-python-sdk-cli
Keywords: streamdeck sdk cli,streamdeck test project,python,sdk,streamdeck,streamdeck-sdk,streamdeck_sdk,stream deck sdk,stream deck,elgato,elgato sdk,elgato stream deck,streamdeck-python-sdk,streamdeck_python_sdk,streamdeck python sdk
Classifier: Programming Language :: Python :: 3.10
Classifier: License :: OSI Approved :: Apache Software License
Classifier: Operating System :: OS Independent
Requires-Python: >=3.8
License-File: LICENSE
